tf_encrypted/primitives/__init__.py
tf_encrypted/primitives/paillier/__init__.py
tf_encrypted/primitives/paillier/primitives.py
tf_encrypted/primitives/sodium/__init__.py
tf_encrypted/primitives/sodium/python/__init__.py
tf_encrypted/primitives/sodium/python/_sodium_module.so
tf_encrypted/primitives/sodium/python/easy_box.py
tf_encrypted/test/__init__.py
tf_encrypted/test/execution_context.py
tf_encrypted_primitives-0.1.1.dist-info/METADATA
tf_encrypted_primitives-0.1.1.dist-info/WHEEL
tf_encrypted_primitives-0.1.1.dist-info/top_level.txt
tf_encrypted_primitives-0.1.1.dist-info/RECORD
